{
"icon-1": {
	"x": 39,
	"y": 38,
	"width": 15,
	"height": 15,
	"pixelRatio": 1
},
"icon-2": {
	"x": 92,
	"y": 25,
	"width": 35,
	"height": 41,
	"pixelRatio": 1
},
"icon-3": {
	"x": 165,
	"y": 30,
	"width": 16,
	"height": 31,
	"pixelRatio": 1
},
"icon-4": {
	"x": 218,
	"y": 28,
	"width": 18,
	"height": 35,
	"pixelRatio": 1
},
"icon-5": {
	"x": 274,
	"y": 30,
	"width": 14,
	"height": 31,
	"pixelRatio": 1
},
"icon-6": {
	"x": 325,
	"y": 21,
	"width": 25,
	"height": 49,
	"pixelRatio": 1
},
"icon-7": {
	"x": 388,
	"y": 29,
	"width": 22,
	"height": 33,
	"pixelRatio": 1
},
"icon-8": {
	"x": 448,
	"y": 28,
	"width": 29,
	"height": 35,
	"pixelRatio": 1
},
"icon-9": {
	"x": 515,
	"y": 32,
	"width": 37,
	"height": 27,
	"pixelRatio": 1
},
"icon-10": {
	"x": 590,
	"y": 29,
	"width": 20,
	"height": 33,
	"pixelRatio": 1
},
"icon-11": {
	"x": 648,
	"y": 25,
	"width": 25,
	"height": 41,
	"pixelRatio": 1
},
"icon-12": {
	"x": 710,
	"y": 26,
	"width": 22,
	"height": 39,
	"pixelRatio": 1
},
"icon-13": {
	"x": 770,
	"y": 28,
	"width": 35,
	"height": 35,
	"pixelRatio": 1
},
"icon-14": {
	"x": 842,
	"y": 28,
	"width": 35,
	"height": 35,
	"pixelRatio": 1
},
"icon-15": {
	"x": 915,
	"y": 40,
	"width": 12,
	"height": 11,
	"pixelRatio": 1
},
"icon-16": {
	"x": 964,
	"y": 30,
	"width": 31,
	"height": 31,
	"pixelRatio": 1
},
"icon-17": {
	"x": 1032,
	"y": 31,
	"width": 30,
	"height": 29,
	"pixelRatio": 1
},
"icon-18": {
	"x": 1100,
	"y": 33,
	"width": 24,
	"height": 25,
	"pixelRatio": 1
},
"icon-19": {
	"x": 1162,
	"y": 40,
	"width": 12,
	"height": 11,
	"pixelRatio": 1
},
"icon-20": {
	"x": 1212,
	"y": 36,
	"width": 19,
	"height": 19,
	"pixelRatio": 1
},
"icon-21": {
	"x": 1268,
	"y": 30,
	"width": 31,
	"height": 31,
	"pixelRatio": 1
},
"icon-22": {
	"x": 1336,
	"y": 34,
	"width": 24,
	"height": 23,
	"pixelRatio": 1
},
"icon-23": {
	"x": 1397,
	"y": 40,
	"width": 12,
	"height": 11,
	"pixelRatio": 1
},
"icon-24": {
	"x": 1446,
	"y": 34,
	"width": 49,
	"height": 23,
	"pixelRatio": 1
},
"icon-25": {
	"x": 1531,
	"y": 26,
	"width": 22,
	"height": 39,
	"pixelRatio": 1
},
"icon-26": {
	"x": 1591,
	"y": 26,
	"width": 26,
	"height": 39,
	"pixelRatio": 1
},
"icon-27": {
	"x": 1655,
	"y": 25,
	"width": 15,
	"height": 39,
	"pixelRatio": 1
},
"icon-28": {
	"x": 1708,
	"y": 31,
	"width": 40,
	"height": 29,
	"pixelRatio": 1
},
"icon-29": {
	"x": 1783,
	"y": 38,
	"width": 35,
	"height": 18,
	"pixelRatio": 1
},
"icon-30": {
	"x": 1853,
	"y": 35,
	"width": 40,
	"height": 21,
	"pixelRatio": 1
},
"icon-31": {
	"x": 1929,
	"y": 8,
	"width": 34,
	"height": 68,
	"pixelRatio": 1
},
"icon-32": {
	"x": 1999,
	"y": 18,
	"width": 20,
	"height": 55,
	"pixelRatio": 1
},
"icon-33": {
	"x": 2056,
	"y": 18,
	"width": 20,
	"height": 55,
	"pixelRatio": 1
},
"icon-34": {
	"x": 2114,
	"y": 22,
	"width": 25,
	"height": 47,
	"pixelRatio": 1
},
"icon-35": {
	"x": 2177,
	"y": 21,
	"width": 34,
	"height": 49,
	"pixelRatio": 1
},
"icon-36": {
	"x": 2249,
	"y": 19,
	"width": 20,
	"height": 53,
	"pixelRatio": 1
},
"icon-37": {
	"x": 2306,
	"y": 17,
	"width": 52,
	"height": 56,
	"pixelRatio": 1
},
"icon-38": {
	"x": 2395,
	"y": 26,
	"width": 25,
	"height": 39,
	"pixelRatio": 1
},
"icon-39": {
	"x": 2456,
	"y": 32,
	"width": 36,
	"height": 27,
	"pixelRatio": 1
},
"icon-40": {
	"x": 25,
	"y": 106,
	"width": 25,
	"height": 48,
	"pixelRatio": 1
},
"icon-41": {
	"x": 89,
	"y": 101,
	"width": 34,
	"height": 59,
	"pixelRatio": 1
},
"icon-42": {
	"x": 162,
	"y": 116,
	"width": 23,
	"height": 29,
	"pixelRatio": 1
},
"icon-43": {
	"x": 224,
	"y": 112,
	"width": 33,
	"height": 37,
	"pixelRatio": 1
},
"icon-44": {
	"x": 297,
	"y": 111,
	"width": 49,
	"height": 39,
	"pixelRatio": 1
},
"icon-45": {
	"x": 385,
	"y": 116,
	"width": 30,
	"height": 29,
	"pixelRatio": 1
},
"icon-46": {
	"x": 454,
	"y": 113,
	"width": 35,
	"height": 35,
	"pixelRatio": 1
},
"icon-47": {
	"x": 528,
	"y": 122,
	"width": 52,
	"height": 17,
	"pixelRatio": 1
},
"icon-48": {
	"x": 619,
	"y": 105,
	"width": 20,
	"height": 50,
	"pixelRatio": 1
},
"icon-49": {
	"x": 678,
	"y": 122,
	"width": 16,
	"height": 16,
	"pixelRatio": 1
},
"icon-50": {
	"x": 731,
	"y": 121,
	"width": 20,
	"height": 19,
	"pixelRatio": 1
},
"icon-51": {
	"x": 789,
	"y": 106,
	"width": 34,
	"height": 49,
	"pixelRatio": 1
},
"icon-52": {
	"x": 862,
	"y": 116,
	"width": 41,
	"height": 29,
	"pixelRatio": 1
},
"icon-53": {
	"x": 943,
	"y": 116,
	"width": 41,
	"height": 29,
	"pixelRatio": 1
},
"icon-54": {
	"x": 1023,
	"y": 112,
	"width": 38,
	"height": 36,
	"pixelRatio": 1
},
"icon-55": {
	"x": 1100,
	"y": 112,
	"width": 37,
	"height": 36,
	"pixelRatio": 1
},
"icon-56": {
	"x": 1176,
	"y": 106,
	"width": 50,
	"height": 49,
	"pixelRatio": 1
},
"icon-57": {
	"x": 1265,
	"y": 127,
	"width": 63,
	"height": 7,
	"pixelRatio": 1
},
"icon-58": {
	"x": 1367,
	"y": 127,
	"width": 64,
	"height": 7,
	"pixelRatio": 1
},
"icon-59": {
	"x": 1468,
	"y": 118,
	"width": 28,
	"height": 25,
	"pixelRatio": 1
},
"icon-60": {
	"x": 1532,
	"y": 118,
	"width": 14,
	"height": 25,
	"pixelRatio": 1
},
"icon-61": {
	"x": 1583,
	"y": 101,
	"width": 11,
	"height": 59,
	"pixelRatio": 1
},
"icon-62": {
	"x": 1630,
	"y": 101,
	"width": 11,
	"height": 59,
	"pixelRatio": 1
},
"icon-63": {
	"x": 1679,
	"y": 120,
	"width": 34,
	"height": 21,
	"pixelRatio": 1
},
"icon-64": {
	"x": 1752,
	"y": 110,
	"width": 96,
	"height": 41,
	"pixelRatio": 1
},
"icon-65": {
	"x": 1888,
	"y": 108,
	"width": 102,
	"height": 45,
	"pixelRatio": 1
},
"icon-66": {
	"x": 2028,
	"y": 110,
	"width": 30,
	"height": 41,
	"pixelRatio": 1
},
"icon-67": {
	"x": 2095,
	"y": 106,
	"width": 30,
	"height": 49,
	"pixelRatio": 1
},
"icon-68": {
	"x": 2146,
	"y": 103,
	"width": 89,
	"height": 57,
	"pixelRatio": 1
},
"icon-69": {
	"x": 2260,
	"y": 104,
	"width": 87,
	"height": 55,
	"pixelRatio": 1
},
"icon-70": {
	"x": 43,
	"y": 195,
	"width": 64,
	"height": 6,
	"pixelRatio": 1
},
"icon-71": {
	"x": 175,
	"y": 193,
	"width": 63,
	"height": 10,
	"pixelRatio": 1
},
"icon-72": {
	"x": 305,
	"y": 195,
	"width": 64,
	"height": 6,
	"pixelRatio": 1
},
"icon-73": {
	"x": 452,
	"y": 195,
	"width": 64,
	"height": 6,
	"pixelRatio": 1
},
"icon-74": {
	"x": 599,
	"y": 195,
	"width": 63,
	"height": 6,
	"pixelRatio": 1
},
"icon-75": {
	"x": 746,
	"y": 195,
	"width": 63,
	"height": 6,
	"pixelRatio": 1
},
"icon-76": {
	"x": 892,
	"y": 192,
	"width": 167,
	"height": 12,
	"pixelRatio": 1
},
"icon-77": {
	"x": 1142,
	"y": 192,
	"width": 170,
	"height": 12,
	"pixelRatio": 1
},
"icon-78": {
	"x": 26,
	"y": 252,
	"width": 81,
	"height": 45,
	"pixelRatio": 1
},
"icon-79": {
	"x": 155,
	"y": 252,
	"width": 80,
	"height": 45,
	"pixelRatio": 1
},
"icon-80": {
	"x": 284,
	"y": 251,
	"width": 81,
	"height": 46,
	"pixelRatio": 1
},
"icon-81": {
	"x": 413,
	"y": 252,
	"width": 81,
	"height": 46,
	"pixelRatio": 1
},
"icon-82": {
	"x": 542,
	"y": 247,
	"width": 117,
	"height": 55,
	"pixelRatio": 1
},
"icon-83": {
	"x": 707,
	"y": 251,
	"width": 81,
	"height": 46,
	"pixelRatio": 1
},
"icon-84": {
	"x": 836,
	"y": 249,
	"width": 79,
	"height": 51,
	"pixelRatio": 1
},
"icon-85": {
	"x": 964,
	"y": 236,
	"width": 114,
	"height": 77,
	"pixelRatio": 1
},
"icon-86": {
	"x": 1127,
	"y": 250,
	"width": 117,
	"height": 49,
	"pixelRatio": 1
},
"icon-87": {
	"x": 1293,
	"y": 252,
	"width": 92,
	"height": 46,
	"pixelRatio": 1
},
"icon-88": {
	"x": 1434,
	"y": 252,
	"width": 86,
	"height": 46,
	"pixelRatio": 1
},
"icon-89": {
	"x": 1568,
	"y": 252,
	"width": 86,
	"height": 46,
	"pixelRatio": 1
},
"icon-90": {
	"x": 1703,
	"y": 272,
	"width": 6,
	"height": 5,
	"pixelRatio": 1
},
"icon-91": {
	"x": 1758,
	"y": 272,
	"width": 64,
	"height": 5,
	"pixelRatio": 1
},
"icon-92": {
	"x": 1871,
	"y": 263,
	"width": 33,
	"height": 23,
	"pixelRatio": 1
},
"icon-93": {
	"x": 1951,
	"y": 260,
	"width": 35,
	"height": 29,
	"pixelRatio": 1
},
"icon-94": {
	"x": 2035,
	"y": 261,
	"width": 18,
	"height": 27,
	"pixelRatio": 1
},
"icon-95": {
	"x": 30,
	"y": 348,
	"width": 77,
	"height": 18,
	"pixelRatio": 1
},
"icon-96": {
	"x": 142,
	"y": 348,
	"width": 77,
	"height": 18,
	"pixelRatio": 1
},
"icon-97": {
	"x": 254,
	"y": 348,
	"width": 76,
	"height": 18,
	"pixelRatio": 1
},
"icon-98": {
	"x": 365,
	"y": 351,
	"width": 77,
	"height": 12,
	"pixelRatio": 1
},
"icon-99": {
	"x": 477,
	"y": 351,
	"width": 76,
	"height": 12,
	"pixelRatio": 1
},
"icon-100": {
	"x": 587,
	"y": 342,
	"width": 53,
	"height": 30,
	"pixelRatio": 1
},
"icon-101": {
	"x": 674,
	"y": 344,
	"width": 52,
	"height": 26,
	"pixelRatio": 1
},
"icon-102": {
	"x": 761,
	"y": 344,
	"width": 50,
	"height": 26,
	"pixelRatio": 1
},
"icon-103": {
	"x": 846,
	"y": 336,
	"width": 44,
	"height": 43,
	"pixelRatio": 1
},
"icon-104": {
	"x": 26,
	"y": 410,
	"width": 128,
	"height": 17,
	"pixelRatio": 1
},
"icon-105": {
	"x": 187,
	"y": 410,
	"width": 128,
	"height": 17,
	"pixelRatio": 1
},
"icon-106": {
	"x": 348,
	"y": 410,
	"width": 128,
	"height": 17,
	"pixelRatio": 1
},
"icon-107": {
	"x": 510,
	"y": 410,
	"width": 128,
	"height": 17,
	"pixelRatio": 1
},
"icon-108": {
	"x": 671,
	"y": 410,
	"width": 128,
	"height": 17,
	"pixelRatio": 1
},
"icon-109": {
	"x": 832,
	"y": 410,
	"width": 128,
	"height": 17,
	"pixelRatio": 1
},
"icon-110": {
	"x": 994,
	"y": 413,
	"width": 11,
	"height": 11,
	"pixelRatio": 1
},
"icon-111": {
	"x": 1038,
	"y": 410,
	"width": 17,
	"height": 17,
	"pixelRatio": 1
},
"icon-112": {
	"x": 1090,
	"y": 412,
	"width": 126,
	"height": 14,
	"pixelRatio": 1
},
"icon-113": {
	"x": 1250,
	"y": 413,
	"width": 128,
	"height": 11,
	"pixelRatio": 1
},
"icon-114": {
	"x": 1411,
	"y": 409,
	"width": 77,
	"height": 19,
	"pixelRatio": 1
},
"icon-115": {
	"x": 1521,
	"y": 414,
	"width": 128,
	"height": 9,
	"pixelRatio": 1
},
"icon-116": {
	"x": 1682,
	"y": 415,
	"width": 128,
	"height": 7,
	"pixelRatio": 1
},
"icon-117": {
	"x": 1844,
	"y": 416,
	"width": 128,
	"height": 5,
	"pixelRatio": 1
},
"icon-118": {
	"x": 2005,
	"y": 414,
	"width": 128,
	"height": 9,
	"pixelRatio": 1
},
"icon-119": {
	"x": 2166,
	"y": 415,
	"width": 128,
	"height": 7,
	"pixelRatio": 1
},
"icon-120": {
	"x": 2327,
	"y": 416,
	"width": 128,
	"height": 5,
	"pixelRatio": 1
},
"icon-121": {
	"x": 20,
	"y": 455,
	"width": 33,
	"height": 42,
	"pixelRatio": 1
},
"icon-122": {
	"x": 82,
	"y": 455,
	"width": 48,
	"height": 42,
	"pixelRatio": 1
},
"icon-123": {
	"x": 159,
	"y": 452,
	"width": 27,
	"height": 48,
	"pixelRatio": 1
},
"icon-124": {
	"x": 216,
	"y": 452,
	"width": 27,
	"height": 48,
	"pixelRatio": 1
},
"icon-125": {
	"x": 273,
	"y": 474,
	"width": 64,
	"height": 5,
	"pixelRatio": 1
},
"icon-126": {
	"x": 366,
	"y": 459,
	"width": 64,
	"height": 34,
	"pixelRatio": 1
},
"icon-127": {
	"x": 460,
	"y": 454,
	"width": 64,
	"height": 45,
	"pixelRatio": 1
},
"icon-128": {
	"x": 554,
	"y": 473,
	"width": 64,
	"height": 6,
	"pixelRatio": 1
},
"icon-129": {
	"x": 648,
	"y": 454,
	"width": 79,
	"height": 45,
	"pixelRatio": 1
},
"icon-130": {
	"x": 757,
	"y": 454,
	"width": 79,
	"height": 45,
	"pixelRatio": 1
},
"icon-131": {
	"x": 866,
	"y": 454,
	"width": 79,
	"height": 45,
	"pixelRatio": 1
},
"icon-132": {
	"x": 975,
	"y": 454,
	"width": 80,
	"height": 45,
	"pixelRatio": 1
},
"icon-133": {
	"x": 1084,
	"y": 454,
	"width": 80,
	"height": 45,
	"pixelRatio": 1
},
"icon-134": {
	"x": 1193,
	"y": 454,
	"width": 80,
	"height": 45,
	"pixelRatio": 1
},
"icon-135": {
	"x": 1303,
	"y": 459,
	"width": 30,
	"height": 34,
	"pixelRatio": 1
},
"icon-136": {
	"x": 1363,
	"y": 454,
	"width": 108,
	"height": 44,
	"pixelRatio": 1
},
"icon-137": {
	"x": 1502,
	"y": 454,
	"width": 78,
	"height": 45,
	"pixelRatio": 1
},
"icon-138": {
	"x": 1606,
	"y": 454,
	"width": 80,
	"height": 45,
	"pixelRatio": 1
},
"icon-139": {
	"x": 1721,
	"y": 476,
	"width": 63,
	"height": 1,
	"pixelRatio": 1
},
"icon-140": {
	"x": 1820,
	"y": 472,
	"width": 64,
	"height": 8,
	"pixelRatio": 1
},
"icon-141": {
	"x": 1915,
	"y": 461,
	"width": 29,
	"height": 28,
	"pixelRatio": 1
},
"icon-142": {
	"x": 1965,
	"y": 461,
	"width": 28,
	"height": 28,
	"pixelRatio": 1
},
"icon-143": {
	"x": 2024,
	"y": 471,
	"width": 8,
	"height": 8,
	"pixelRatio": 1
},
"icon-144": {
	"x": 18,
	"y": 563,
	"width": 64,
	"height": 1,
	"pixelRatio": 1
},
"icon-145": {
	"x": 108,
	"y": 563,
	"width": 63,
	"height": 1,
	"pixelRatio": 1
},
"icon-146": {
	"x": 196,
	"y": 557,
	"width": 17,
	"height": 17,
	"pixelRatio": 1
},
"icon-147": {
	"x": 238,
	"y": 556,
	"width": 12,
	"height": 15,
	"pixelRatio": 1
},
"icon-148": {
	"x": 275,
	"y": 561,
	"width": 9,
	"height": 9,
	"pixelRatio": 1
},
"icon-149": {
	"x": 309,
	"y": 559,
	"width": 12,
	"height": 12,
	"pixelRatio": 1
},
"icon-150": {
	"x": 345,
	"y": 552,
	"width": 35,
	"height": 23,
	"pixelRatio": 1
},
"icon-151": {
	"x": 404,
	"y": 552,
	"width": 35,
	"height": 23,
	"pixelRatio": 1
},
"icon-152": {
	"x": 464,
	"y": 563,
	"width": 63,
	"height": 1,
	"pixelRatio": 1
},
"icon-153": {
	"x": 552,
	"y": 558,
	"width": 11,
	"height": 11,
	"pixelRatio": 1
},
"icon-154": {
	"x": 587,
	"y": 559,
	"width": 9,
	"height": 9,
	"pixelRatio": 1
},
"icon-155": {
	"x": 621,
	"y": 546,
	"width": 69,
	"height": 35,
	"pixelRatio": 1
},
"icon-156": {
	"x": 714,
	"y": 540,
	"width": 80,
	"height": 47,
	"pixelRatio": 1
},
"icon-157": {
	"x": 819,
	"y": 541,
	"width": 79,
	"height": 45,
	"pixelRatio": 1
},
"icon-158": {
	"x": 922,
	"y": 541,
	"width": 80,
	"height": 45,
	"pixelRatio": 1
},
"icon-159": {
	"x": 1025,
	"y": 563,
	"width": 65,
	"height": 1,
	"pixelRatio": 1
},
"icon-160": {
	"x": 1115,
	"y": 541,
	"width": 79,
	"height": 45,
	"pixelRatio": 1
},
"icon-161": {
	"x": 1218,
	"y": 541,
	"width": 80,
	"height": 45,
	"pixelRatio": 1
},
"icon-162": {
	"x": 1322,
	"y": 541,
	"width": 79,
	"height": 45,
	"pixelRatio": 1
},
"icon-163": {
	"x": 1426,
	"y": 545,
	"width": 23,
	"height": 31,
	"pixelRatio": 1
},
"icon-164": {
	"x": 1474,
	"y": 560,
	"width": 17,
	"height": 15,
	"pixelRatio": 1
},
"icon-165": {
	"x": 1516,
	"y": 555,
	"width": 39,
	"height": 22,
	"pixelRatio": 1
},
"icon-166": {
	"x": 1580,
	"y": 548,
	"width": 30,
	"height": 32,
	"pixelRatio": 1
},
"icon-167": {
	"x": 1635,
	"y": 542,
	"width": 33,
	"height": 42,
	"pixelRatio": 1
},
"icon-168": {
	"x": 1692,
	"y": 563,
	"width": 65,
	"height": 1,
	"pixelRatio": 1
},
"icon-169": {
	"x": 1782,
	"y": 563,
	"width": 64,
	"height": 1,
	"pixelRatio": 1
},
"icon-170": {
	"x": 20,
	"y": 643,
	"width": 9,
	"height": 9,
	"pixelRatio": 1
},
"icon-171": {
	"x": 54,
	"y": 639,
	"width": 17,
	"height": 15,
	"pixelRatio": 1
},
"icon-172": {
	"x": 96,
	"y": 641,
	"width": 24,
	"height": 13,
	"pixelRatio": 1
},
"icon-173": {
	"x": 144,
	"y": 624,
	"width": 8,
	"height": 47,
	"pixelRatio": 1
},
"icon-174": {
	"x": 177,
	"y": 624,
	"width": 8,
	"height": 47,
	"pixelRatio": 1
},
"icon-175": {
	"x": 210,
	"y": 640,
	"width": 16,
	"height": 15,
	"pixelRatio": 1
},
"icon-176": {
	"x": 251,
	"y": 644,
	"width": 64,
	"height": 7,
	"pixelRatio": 1
},
"icon-177": {
	"x": 340,
	"y": 633,
	"width": 128,
	"height": 29,
	"pixelRatio": 1
},
"icon-178": {
	"x": 493,
	"y": 634,
	"width": 128,
	"height": 27,
	"pixelRatio": 1
},
"icon-179": {
	"x": 646,
	"y": 643,
	"width": 64,
	"height": 9,
	"pixelRatio": 1
},
"icon-180": {
	"x": 735,
	"y": 625,
	"width": 81,
	"height": 45,
	"pixelRatio": 1
},
"icon-181": {
	"x": 840,
	"y": 625,
	"width": 81,
	"height": 45,
	"pixelRatio": 1
},
"icon-182": {
	"x": 945,
	"y": 625,
	"width": 81,
	"height": 45,
	"pixelRatio": 1
},
"icon-183": {
	"x": 1050,
	"y": 640,
	"width": 18,
	"height": 17,
	"pixelRatio": 1
},
"icon-184": {
	"x": 1093,
	"y": 621,
	"width": 57,
	"height": 56,
	"pixelRatio": 1
},
"icon-185": {
	"x": 1173,
	"y": 631,
	"width": 37,
	"height": 36,
	"pixelRatio": 1
},
"icon-186": {
	"x": 1232,
	"y": 631,
	"width": 37,
	"height": 36,
	"pixelRatio": 1
},
"icon-187": {
	"x": 1301,
	"y": 624,
	"width": 80,
	"height": 45,
	"pixelRatio": 1
}
}
